Metadata-Version: 1.1
Name: milon
Version: 0.0.1
Summary: A hebrew dictionary
Home-page: UNKNOWN
Author: Alejandro Gallo
Author-email: aamsgallo@gmail.com
License: GPLv3
Keywords: hebrew,dictionary,arabic,semitic
Platform: linux
Platform: osx
Classifier: Environment :: Console
Classifier: Environment :: Console :: Curses
Classifier: Intended Audience :: Developers
Classifier: Intended Audience :: System Administrators
Classifier: License :: OSI Approved :: GNU General Public License v3 (GPLv3)
Classifier: Operating System :: MacOS
Classifier: Operating System :: POSIX
Classifier: Operating System :: Unix
Classifier: Programming Language :: Python :: 2.6
Classifier: Programming Language :: Python :: 2.7
Classifier: Programming Language :: Python :: 3.3
Classifier: Programming Language :: Python :: 3.4
Classifier: Programming Language :: Python :: 3.5
Classifier: Programming Language :: Python :: 3.6
Classifier: Topic :: Utilities
